Workbook
Name NativeTimeline_Fecha: #N/A
Name SegmentaciónDeDatos_Categoría: #N/A
Name SegmentaciónDeDatos_Categoría1: #N/A
Name SegmentaciónDeDatos_Provincia: #N/A
Name SegmentaciónDeDatos_Vendedor: #N/A
Name SegmentaciónDeDatos_Vendedor1: #N/A

Sheet BaseDeDatos
B2: Documento | C2: Fecha | D2: Id Cliente | E2: Cliente | F2: Ciudad | G2: Provincia | H2: Vendedor | I2: Empresa | J2: Forma de pago | K2: Producto | L2: Categoría | M2: Precio | N2: Cantidad | O2: Ventas
B3: 1 | C3: 43930 | D3: 9259377217 | E3: Empresa AA | F3: Cuenca | G3: Azuay | H3: Mayra Aguilar Sepúlveda | I3: Empresa de embarque B | J3: Cheque | K3: Cerveza | L3: Bebidas | M3: 14 | N3: 10 | O3: =BaseDeDatos!$M3*BaseDeDatos!$N3 -> 140
B4: 2 | C4: 44068 | D4: 6185253419 | E4: Empresa AA | F4: Cuenca | G4: Azuay | H4: Mayra Aguilar Sepúlveda | I4: Empresa de embarque B | J4: Cheque | K4: Ciruelas secas | L4: Frutas secas | M4: 34 | N4: 1 | O4: =BaseDeDatos!$M4*BaseDeDatos!$N4 -> 34
B5: 3 | C5: 43908 | D5: 2308885942 | E5: Empresa D | F5: Azogues | G5: Canar | H5: Andrés González Rico | I5: Empresa de embarque A | J5: Tarjeta de crédito | K5: Peras secas | L5: Frutas secas | M5: 14 | N5: 57 | O5: =BaseDeDatos!$M5*BaseDeDatos!$N5 -> 798
B6: 4 | C6: 43974 | D6: 6199717898 | E6: Empresa D | F6: Azogues | G6: Canar | H6: Andrés González Rico | I6: Empresa de embarque A | J6: Tarjeta de crédito | K6: Manzanas secas | L6: Frutas secas | M6: 16 | N6: 72 | O6: =BaseDeDatos!$M6*BaseDeDatos!$N6 -> 1152
B7: 5 | C7: 43944 | D7: 5540683029 | E7: Empresa D | F7: Azogues | G7: Canar | H7: Andrés González Rico | I7: Empresa de embarque A | J7: Tarjeta de crédito | K7: Ciruelas secas | L7: Frutas secas | M7: 12 | N7: 68 | O7: =BaseDeDatos!$M7*BaseDeDatos!$N7 -> 816
B8: 6 | C8: 44184 | D8: 6343955045 | E8: Empresa L | F8: Cuenca | G8: Azuay | H8: Mayra Aguilar Sepúlveda | I8: Empresa de embarque B | J8: Tarjeta de crédito | K8: Té chai | L8: Bebidas | M8: 22 | N8: 29 | O8: =BaseDeDatos!$M8*BaseDeDatos!$N8 -> 638
B9: 7 | C9: 44133 | D9: 1572125717 | E9: Empresa L | F9: Cuenca | G9: Azuay | H9: Mayra Aguilar Sepúlveda | I9: Empresa de embarque B | J9: Tarjeta de crédito | K9: Café | L9: Bebidas | M9: 42 | N9: 41 | O9: =BaseDeDatos!$M9*BaseDeDatos!$N9 -> 1722
B10: 8 | C10: 43863 | D10: 3776895536 | E10: Empresa H | F10: Riobamba | G10: Chimborazo | H10: Nancy Gil de la Peña | I10: Empresa de embarque C | J10: Tarjeta de crédito | K10: Galletas de chocolate | L10: Productos horneados | M10: 11 | N10: 18 | O10: =BaseDeDatos!$M10*BaseDeDatos!$N10 -> 198
B11: 9 | C11: 44158 | D11: 390733860 | E11: Empresa D | F11: Azogues | G11: Canar | H11: Andrés González Rico | I11: Empresa de embarque C | J11: Cheque | K11: Galletas de chocolate | L11: Productos horneados | M11: 29 | N11: 73 | O11: =BaseDeDatos!$M11*BaseDeDatos!$N11 -> 2117
B12: 10 | C12: 43863 | D12: 2456709195 | E12: Empresa CC | F12: Guayaquil | G12: Guayas | H12: José de Jesús Morales | I12: Empresa de embarque B | J12: Cheque | K12: Chocolate | L12: Dulces | M12: 12 | N12: 79 | O12: =BaseDeDatos!$M12*BaseDeDatos!$N12 -> 948
B13: 11 | C13: 43999 | D13: 5766090086 | E13: Empresa C | F13: Machala | G13: El Oro | H13: Mayra Aguilar Sepúlveda | I13: Empresa de embarque B | J13: Efectivo | K13: Almejas | L13: Sopas | M13: 28 | N13: 37 | O13: =BaseDeDatos!$M13*BaseDeDatos!$N13 -> 1036
B14: 12 | C14: 44045 | D14: 4872781256 | E14: Empresa F | F14: Ibarra | G14: Imbabura | H14: Luis Miguel Valdés Garza | I14: Empresa de embarque B | J14: Tarjeta de crédito | K14: Salsa curry | L14: Salsas | M14: 33 | N14: 64 | O14: =BaseDeDatos!$M14*BaseDeDatos!$N14 -> 2112
... B17: 15 | C17: 44037 | D17: 8539365209 | E17: Empresa J | F17: Esmeraldas | G17: Esmeraldas | H17: Laura Gutiérrez Saenz | I17: Empresa de embarque B | J17: Tarjeta de crédito | K17: Té verde | L17: Bebidas | M17: 41 | N17: 96 | O17: =BaseDeDatos!$M17*BaseDeDatos!$N17 -> 3936
B18: 16 | C18: 44009 | D18: 6983099686 | E18: Empresa G | F18: Guaranda | G18: Guaranda | H18: Nancy Gil de la Peña | K18: Café | L18: Bebidas | M18: 45 | N18: 97 | O18: =BaseDeDatos!$M18*BaseDeDatos!$N18 -> 4365
B19: 17 | C19: 44065 | D19: 3008945605 | E19: Empresa J | F19: Esmeraldas | G19: Esmeraldas | H19: Laura Gutiérrez Saenz | I19: Empresa de embarque A | K19: Jalea de fresa | L19: Mermeladas y jaleas | M19: 26 | N19: 65 | O19: =BaseDeDatos!$M19*BaseDeDatos!$N19 -> 1690
B20: 18 | C20: 43937 | D20: 5388305959 | E20: Empresa J | F20: Esmeraldas | G20: Esmeraldas | H20: Laura Gutiérrez Saenz | I20: Empresa de embarque A | K20: Condimento cajún | L20: Condimentos | M20: 40 | N20: 88 | O20: =BaseDeDatos!$M20*BaseDeDatos!$N20 -> 3520
B21: 19 | C21: 44172 | D21: 438272084 | E21: Empresa J | F21: Esmeraldas | G21: Esmeraldas | H21: Laura Gutiérrez Saenz | I21: Empresa de embarque A | K21: Galletas de chocolate | L21: Productos horneados | M21: 12 | N21: 60 | O21: =BaseDeDatos!$M21*BaseDeDatos!$N21 -> 720
B22: 20 | C22: 43875 | D22: 2536792311 | E22: Empresa K | F22: Quito | G22: Pichincha | H22: Ana del Valle Hinojosa | I22: Empresa de embarque C | K22: Ciruelas secas | L22: Frutas secas | M22: 35 | N22: 96 | O22: =BaseDeDatos!$M22*BaseDeDatos!$N22 -> 3360
B23: 21 | C23: 44138 | D23: 7813757711 | E23: Empresa K | F23: Quito | G23: Pichincha | H23: Ana del Valle Hinojosa | I23: Empresa de embarque C | K23: Té verde | L23: Bebidas | M23: 20 | N23: 50 | O23: =BaseDeDatos!$M23*BaseDeDatos!$N23 -> 1000
B24: 22 | C24: 43918 | D24: 4786931679 | E24: Empresa A | F24: Ambato | G24: Tungurahua | H24: Nancy Gil de la Peña | K24: Té chai | L24: Bebidas | M24: 50 | N24: 75 | O24: =BaseDeDatos!$M24*BaseDeDatos!$N24 -> 3750
B25: 23 | C25: 44039 | D25: 3021659728 | E25: Empresa A | F25: Ambato | G25: Tungurahua | H25: Nancy Gil de la Peña | K25: Café | L25: Bebidas | M25: 21 | N25: 4 | O25: =BaseDeDatos!$M25*BaseDeDatos!$N25 -> 84
B26: 24 | C26: 43993 | D26: 2591950684 | E26: Empresa A | F26: Ambato | G26: Tungurahua | H26: Nancy Gil de la Peña | K26: Té verde | L26: Bebidas | M26: 43 | N26: 18 | O26: =BaseDeDatos!$M26*BaseDeDatos!$N26 -> 774
B27: 25 | C27: 43885 | D27: 9326361454 | E27: Empresa BB | F27: Manta | G27: Manabi | H27: Ana del Valle Hinojosa | I27: Empresa de embarque C | J27: Tarjeta de crédito | K27: Almejas | L27: Sopas | M27: 26 | N27: 49 | O27: =BaseDeDatos!$M27*BaseDeDatos!$N27 -> 1274
B28: 26 | C28: 44055 | D28: 3769138349 | E28: Empresa BB | F28: Manta | G28: Manabi | H28: Ana del Valle Hinojosa | I28: Empresa de embarque C | J28: Tarjeta de crédito | K28: Carne de cangrejo | L28: Carne enlatada | M28: 39 | N28: 21 | O28: =BaseDeDatos!$M28*BaseDeDatos!$N28 -> 819
B29: 27 | C29: 43908 | D29: 5871657714 | E29: Empresa I | F29: Guayaquil | G29: Guayas | H29: Robert Zárate Carrillo | I29: Empresa de embarque A | J29: Cheque | K29: Ravioli | L29: Pasta | M29: 33 | N29: 8 | O29: =BaseDeDatos!$M29*BaseDeDatos!$N29 -> 264
B30: 28 | C30: 43965 | D30: 1534553307 | E30: Empresa I | F30: Guayaquil | G30: Guayas | H30: Robert Zárate Carrillo | I30: Empresa de embarque A | J30: Cheque | K30: Mozzarella | L30: Productos lácteos | M30: 46 | N30: 82 | O30: =BaseDeDatos!$M30*BaseDeDatos!$N30 -> 3772
B31: 29 | C31: 44146 | D31: 8474620707 | E31: Empresa F | F31: Ibarra | G31: Imbabura | H31: Luis Miguel Valdés Garza | I31: Empresa de embarque B | J31: Tarjeta de crédito | K31: Cerveza | L31: Bebidas | M31: 32 | N31: 75 | O31: =BaseDeDatos!$M31*BaseDeDatos!$N31 -> 2400
B32: 30 | C32: 44144 | D32: 3530767380 | E32: Empresa H | F32: Riobamba | G32: Chimborazo | H32: Nancy Gil de la Peña | I32: Empresa de embarque B | J32: Cheque | K32: Salsa curry | L32: Salsas | M32: 34 | N32: 3 | O32: =BaseDeDatos!$M32*BaseDeDatos!$N32 -> 102
B33: 31 | C33: 43845 | D33: 6673950624 | E33: Empresa C | F33: Machala | G33: El Oro | H33: Mayra Aguilar Sepúlveda | I33: Empresa de embarque B | J33: Efectivo | K33: Jarabe | L33: Condimentos | M33: 24 | N33: 33 | O33: =BaseDeDatos!$M33*BaseDeDatos!$N33 -> 792
B34: 32 | C34: 43967 | D34: 7137547321 | E34: Empresa C | F34: Machala | G34: El Oro | H34: Mayra Aguilar Sepúlveda | I34: Empresa de embarque B | J34: Efectivo | K34: Salsa curry | L34: Salsas | M34: 21 | N34: 51 | O34: =BaseDeDatos!$M34*BaseDeDatos!$N34 -> 1071
B35: 33 | C35: 43862 | D35: 9655985375 | E35: Empresa F | F35: Ibarra | G35: Imbabura | H35: Luis Miguel Valdés Garza | I35: Empresa de embarque B | J35: Tarjeta de crédito | L35: Tarifa de envío
B36: 34 | C36: 44167 | D36: 299812367 | E36: Empresa BB | F36: Manta | G36: Manabi | H36: Ana del Valle Hinojosa | I36: Empresa de embarque C | J36: Cheque | L36: Tarifa de envío
B37: 35 | C37: 43870 | D37: 7779151222 | E37: Empresa H | F37: Riobamba | G37: Chimborazo | H37: Nancy Gil de la Peña | I37: Empresa de embarque C | J37: Cheque | L37: Tarifa de envío
B38: 36 | C38: 44192 | D38: 9282360094 | E38: Empresa J | F38: Esmeraldas | G38: Esmeraldas | H38: Laura Gutiérrez Saenz | I38: Empresa de embarque B | J38: Tarjeta de crédito | K38: Almendras | L38: Frutas secas | M38: 140 | N38: 47 | O38: =BaseDeDatos!$M38*BaseDeDatos!$N38 -> 6580
B39: 37 | C39: 43982 | D39: 6935804403 | E39: Empresa J | F39: Esmeraldas | G39: Esmeraldas | H39: Laura Gutiérrez Saenz | I39: Empresa de embarque A | K39: Ciruelas secas | L39: Frutas secas | M39: 49 | N39: 49 | O39: =BaseDeDatos!$M39*BaseDeDatos!$N39 -> 2401
B40: 38 | C40: 43952 | D40: 3650322132 | E40: Empresa K | F40: Quito | G40: Pichincha | H40: Ana del Valle Hinojosa | I40: Empresa de embarque C | K40: Salsa curry | L40: Salsas | M40: 560 | N40: 72 | O40: =BaseDeDatos!$M40*BaseDeDatos!$N40 -> 40320
B41: 39 | C41: 43965 | D41: 1985754250 | E41: Empresa A | F41: Ambato | G41: Tungurahua | H41: Nancy Gil de la Peña | I41: Empresa de embarque C | K41: Carne de cangrejo | L41: Carne enlatada | M41: 257.6 | N41: 13 | O41: =BaseDeDatos!$M41*BaseDeDatos!$N41 -> 3348.8
B42: 40 | C42: 44090 | D42: 7293507918 | E42: Empresa BB | F42: Manta | G42: Manabi | H42: Ana del Valle Hinojosa | I42: Empresa de embarque C | J42: Tarjeta de crédito | K42: Café | L42: Bebidas | M42: 644 | N42: 32 | O42: =BaseDeDatos!$M42*BaseDeDatos!$N42 -> 20608
B43: 41 | C43: 43983 | D43: 3459323228 | E43: Empresa I | F43: Guayaquil | G43: Guayas | H43: Robert Zárate Carrillo | I43: Empresa de embarque A | J43: Cheque | K43: Almejas | L43: Sopas | M43: 135.1 | N43: 27 | O43: =BaseDeDatos!$M43*BaseDeDatos!$N43 -> 3647.7
B44: 42 | C44: 43999 | D44: 1144627655 | E44: Empresa F | F44: Ibarra | G44: Imbabura | H44: Luis Miguel Valdés Garza | I44: Empresa de embarque B | J44: Tarjeta de crédito | K44: Chocolate | L44: Dulces | M44: 178.5 | N44: 71 | O44: =BaseDeDatos!$M44*BaseDeDatos!$N44 -> 12673.5
B45: 43 | C45: 44070 | D45: 3986713828 | E45: Empresa H | F45: Riobamba | G45: Chimborazo | H45: Nancy Gil de la Peña | I45: Empresa de embarque B | J45: Cheque | K45: Chocolate | L45: Dulces | M45: 178.5 | N45: 13 | O45: =BaseDeDatos!$M45*BaseDeDatos!$N45 -> 2320.5
B46: 44 | C46: 43998 | D46: 9350633665 | E46: Empresa Y | F46: Esmeraldas | G46: Esmeraldas | H46: Laura Gutiérrez Saenz | I46: Empresa de embarque A | J46: Efectivo | K46: Condimento cajún | L46: Condimentos | M46: 308 | N46: 98 | O46: =BaseDeDatos!$M46*BaseDeDatos!$N46 -> 30184
B47: 45 | C47: 44129 | D47: 4918639925 | E47: Empresa Z | F47: Quito | G47: Pichincha | H47: Ana del Valle Hinojosa | I47: Empresa de embarque C | J47: Tarjeta de crédito | K47: Jalea de fresa | L47: Mermeladas y jaleas | M47: 350 | N47: 21 | O47: =BaseDeDatos!$M47*BaseDeDatos!$N47 -> 7350
B48: 46 | C48: 44165 | D48: 9630006862 | E48: Empresa CC | F48: Guayaquil | G48: Guayas | H48: José de Jesús Morales | I48: Empresa de embarque B | J48: Cheque | K48: Cóctel de frutas | L48: Frutas y vegetales | M48: 546 | N48: 26 | O48: =BaseDeDatos!$M48*BaseDeDatos!$N48 -> 14196
B49: 47 | C49: 43920 | D49: 9029002933 | E49: Empresa F | F49: Ibarra | G49: Imbabura | H49: Luis Miguel Valdés Garza | I49: Empresa de embarque C | J49: Cheque | K49: Peras secas | L49: Frutas secas | M49: 420 | N49: 96 | O49: =BaseDeDatos!$M49*BaseDeDatos!$N49 -> 40320
B50: 48 | C50: 43880 | D50: 5702300844 | E50: Empresa F | F50: Ibarra | G50: Imbabura | H50: Luis Miguel Valdés Garza | I50: Empresa de embarque C | J50: Cheque | K50: Manzanas secas | L50: Frutas secas | M50: 742 | N50: 16 | O50: =BaseDeDatos!$M50*BaseDeDatos!$N50 -> 11872
B51: 49 | C51: 43922 | D51: 6885713027 | E51: Empresa D | F51: Azogues | G51: Canar | H51: Andrés González Rico | K51: Pasta penne | L51: Pasta | M51: 532 | N51: 96 | O51: =BaseDeDatos!$M51*BaseDeDatos!$N51 -> 51072
B52: 50 | C52: 43861 | D52: 5156178317 | E52: Empresa C | F52: Machala | G52: El Oro | H52: Mayra Aguilar Sepúlveda | K52: Té verde | L52: Bebidas | M52: 41.86 | N52: 75 | O52: =BaseDeDatos!$M52*BaseDeDatos!$N52 -> 3139.5
B53: 51 | C53: 43992 | D53: 9993785470 | E53: Empresa I | F53: Guayaquil | G53: Guayas | H53: Robert Zárate Carrillo | I53: Empresa de embarque A | J53: Cheque | K53: Ravioli | L53: Pasta | M53: 273 | N53: 55 | O53: =BaseDeDatos!$M53*BaseDeDatos!$N53 -> 15015
B54: 52 | C54: 44107 | D54: 2344903076 | E54: Empresa I | F54: Guayaquil | G54: Guayas | H54: Robert Zárate Carrillo | I54: Empresa de embarque A | J54: Cheque | K54: Mozzarella | L54: Productos lácteos | M54: 487.2 | N54: 11 | O54: =BaseDeDatos!$M54*BaseDeDatos!$N54 -> 5359.2
B55: 53 | C55: 44123 | D55: 5773601950 | E55: Empresa F | F55: Ibarra | G55: Imbabura | H55: Luis Miguel Valdés Garza | I55: Empresa de embarque B | J55: Tarjeta de crédito | K55: Cerveza | L55: Bebidas | M55: 196 | N55: 53 | O55: =BaseDeDatos!$M55*BaseDeDatos!$N55 -> 10388
B56: 54 | C56: 44088 | D56: 4818078168 | E56: Empresa H | F56: Riobamba | G56: Chimborazo | H56: Nancy Gil de la Peña | I56: Empresa de embarque B | J56: Cheque | K56: Salsa curry | L56: Salsas | M56: 560 | N56: 85 | O56: =BaseDeDatos!$M56*BaseDeDatos!$N56 -> 47600
B57: 55 | C57: 44178 | D57: 9107195581 | E57: Empresa H | F57: Riobamba | G57: Chimborazo | H57: Nancy Gil de la Peña | I57: Empresa de embarque B | J57: Cheque | K57: Galletas de chocolate | L57: Productos horneados | M57: 128.8 | N57: 97 | O57: =BaseDeDatos!$M57*BaseDeDatos!$N57 -> 12493.6
B58: 56 | C58: 43964 | D58: 5806733138 | E58: Empresa Y | F58: Esmeraldas | G58: Esmeraldas | H58: Laura Gutiérrez Saenz | I58: Empresa de embarque A | J58: Efectivo | K58: Bolillos | L58: Productos horneados | M58: 140 | N58: 46 | O58: =BaseDeDatos!$M58*BaseDeDatos!$N58 -> 6440
B59: 57 | C59: 43882 | D59: 3059258597 | E59: Empresa Z | F59: Quito | G59: Pichincha | H59: Ana del Valle Hinojosa | I59: Empresa de embarque C | J59: Tarjeta de crédito | K59: Aceite de oliva | L59: Aceite | M59: 298.9 | N59: 97 | O59: =BaseDeDatos!$M59*BaseDeDatos!$N59 -> 28993.3
B60: 58 | C60: 44154 | D60: 586395005 | E60: Empresa Z | F60: Quito | G60: Pichincha | H60: Ana del Valle Hinojosa | I60: Empresa de embarque C | J60: Tarjeta de crédito | K60: Almejas | L60: Sopas | M60: 135.1 | N60: 97 | O60: =BaseDeDatos!$M60*BaseDeDatos!$N60 -> 13104.7
B61: 59 | C61: 44075 | D61: 9281389647 | E61: Empresa Z | F61: Quito | G61: Pichincha | H61: Ana del Valle Hinojosa | I61: Empresa de embarque C | J61: Tarjeta de crédito | K61: Carne de cangrejo | L61: Carne enlatada | M61: 257.6 | N61: 65 | O61: =BaseDeDatos!$M61*BaseDeDatos!$N61 -> 16744
B62: 60 | C62: 44171 | D62: 2230409971 | E62: Empresa CC | F62: Guayaquil | G62: Guayas | H62: José de Jesús Morales | I62: Empresa de embarque B | J62: Cheque | K62: Cerveza | L62: Bebidas | M62: 196 | N62: 72 | O62: =BaseDeDatos!$M62*BaseDeDatos!$N62 -> 14112
B63: 61 | C63: 43982 | D63: 498762200 | E63: Empresa F | F63: Ibarra | G63: Imbabura | H63: Luis Miguel Valdés Garza | I63: Empresa de embarque C | J63: Cheque | K63: Chocolate | L63: Dulces | M63: 178.5 | N63: 16 | O63: =BaseDeDatos!$M63*BaseDeDatos!$N63 -> 2856
B64: 62 | C64: 43855 | D64: 5059332572 | E64: Empresa D | F64: Azogues | G64: Canar | H64: Andrés González Rico | I64: Empresa de embarque A | J64: Tarjeta de crédito | K64: Mermelada de zarzamora | L64: Mermeladas y jaleas | M64: 1134 | N64: 77 | O64: =BaseDeDatos!$M64*BaseDeDatos!$N64 -> 87318
... B69: 67 | C69: 43945 | D69: 6476704094 | E69: Empresa J | F69: Esmeraldas | G69: Esmeraldas | H69: Laura Gutiérrez Saenz | I69: Empresa de embarque B | J69: Tarjeta de crédito | K69: Almendras | L69: Frutas secas | M69: 140 | N69: 55 | O69: =BaseDeDatos!$M69*BaseDeDatos!$N69 -> 7700
B70: 68 | C70: 44052 | D70: 289513623 | E70: Empresa J | F70: Esmeraldas | G70: Esmeraldas | H70: Laura Gutiérrez Saenz | I70: Empresa de embarque A | K70: Ciruelas secas | L70: Frutas secas | M70: 49 | N70: 21 | O70: =BaseDeDatos!$M70*BaseDeDatos!$N70 -> 1029
B71: 69 | C71: 44115 | D71: 4360909288 | E71: Empresa K | F71: Quito | G71: Pichincha | H71: Ana del Valle Hinojosa | I71: Empresa de embarque C | K71: Salsa curry | L71: Salsas | M71: 560 | N71: 67 | O71: =BaseDeDatos!$M71*BaseDeDatos!$N71 -> 37520
B72: 70 | C72: 43966 | D72: 1569352924 | E72: Empresa A | F72: Ambato | G72: Tungurahua | H72: Nancy Gil de la Peña | I72: Empresa de embarque C | K72: Carne de cangrejo | L72: Carne enlatada | M72: 257.6 | N72: 75 | O72: =BaseDeDatos!$M72*BaseDeDatos!$N72 -> 19320
B73: 71 | C73: 43962 | D73: 4417023777 | E73: Empresa BB | F73: Manta | G73: Manabi | H73: Ana del Valle Hinojosa | I73: Empresa de embarque C | J73: Tarjeta de crédito | K73: Café | L73: Bebidas | M73: 644 | N73: 17 | O73: =BaseDeDatos!$M73*BaseDeDatos!$N73 -> 10948
B74: 72 | C74: 43845 | D74: 5213348963 | E74: Empresa D | F74: Azogues | G74: Canar | H74: Andrés González Rico | I74: Empresa de embarque A | J74: Tarjeta de crédito | K74: Ciruelas secas | L74: Frutas secas | M74: 49 | N74: 48 | O74: =BaseDeDatos!$M74*BaseDeDatos!$N74 -> 2352
B75: 73 | C75: 44010 | D75: 6039525395 | E75: Empresa L | F75: Cuenca | G75: Azuay | H75: Mayra Aguilar Sepúlveda | I75: Empresa de embarque B | J75: Tarjeta de crédito | K75: Té chai | L75: Bebidas | M75: 252 | N75: 74 | O75: =BaseDeDatos!$M75*BaseDeDatos!$N75 -> 18648
B76: 74 | C76: 44123 | D76: 7564866770 | E76: Empresa L | F76: Cuenca | G76: Azuay | H76: Mayra Aguilar Sepúlveda | I76: Empresa de embarque B | J76: Tarjeta de crédito | K76: Café | L76: Bebidas | M76: 644 | N76: 96 | O76: =BaseDeDatos!$M76*BaseDeDatos!$N76 -> 61824
B77: 75 | C77: 43976 | D77: 9161740728 | E77: Empresa H | F77: Riobamba | G77: Chimborazo | H77: Nancy Gil de la Peña | I77: Empresa de embarque C | J77: Tarjeta de crédito | K77: Galletas de chocolate | L77: Productos horneados | M77: 128.8 | N77: 12 | O77: =BaseDeDatos!$M77*BaseDeDatos!$N77 -> 1545.6
B78: 76 | C78: 43939 | D78: 5854661633 | E78: Empresa D | F78: Azogues | G78: Canar | H78: Andrés González Rico | I78: Empresa de embarque C | J78: Cheque | K78: Galletas de chocolate | L78: Productos horneados | M78: 128.8 | N78: 62 | O78: =BaseDeDatos!$M78*BaseDeDatos!$N78 -> 7985.6
B79: 77 | C79: 43995 | D79: 9782824487 | E79: Empresa CC | F79: Guayaquil | G79: Guayas | H79: José de Jesús Morales | I79: Empresa de embarque B | J79: Cheque | K79: Chocolate | L79: Dulces | M79: 178.5 | N79: 35 | O79: =BaseDeDatos!$M79*BaseDeDatos!$N79 -> 6247.5
B80: 78 | C80: 43888 | D80: 5368581132 | E80: Empresa C | F80: Machala | G80: El Oro | H80: Mayra Aguilar Sepúlveda | I80: Empresa de embarque B | J80: Efectivo | K80: Almejas | L80: Sopas | M80: 135.1 | N80: 95 | O80: =BaseDeDatos!$M80*BaseDeDatos!$N80 -> 12834.5
B81: 79 | C81: 43991 | D81: 1972466220 | E81: Empresa F | F81: Ibarra | G81: Imbabura | H81: Luis Miguel Valdés Garza | I81: Empresa de embarque B | J81: Tarjeta de crédito | K81: Salsa curry | L81: Salsas | M81: 560 | N81: 17 | O81: =BaseDeDatos!$M81*BaseDeDatos!$N81 -> 9520
B82: 80 | C82: 44149 | D82: 6835780904 | E82: Empresa BB | F82: Manta | G82: Manabi | H82: Ana del Valle Hinojosa | I82: Empresa de embarque C | J82: Cheque | K82: Café | L82: Bebidas | M82: 644 | N82: 96 | O82: =BaseDeDatos!$M82*BaseDeDatos!$N82 -> 61824
B83: 81 | C83: 44029 | D83: 9361876990 | E83: Empresa H | F83: Riobamba | G83: Chimborazo | H83: Nancy Gil de la Peña | I83: Empresa de embarque C | J83: Cheque | K83: Chocolate | L83: Dulces | M83: 178.5 | N83: 83 | O83: =BaseDeDatos!$M83*BaseDeDatos!$N83 -> 14815.5
B84: 82 | C84: 43831 | D84: 7655628230 | E84: Empresa J | F84: Esmeraldas | G84: Esmeraldas | H84: Laura Gutiérrez Saenz | I84: Empresa de embarque B | J84: Tarjeta de crédito | K84: Té verde | L84: Bebidas | M84: 41.86 | N84: 88 | O84: =BaseDeDatos!$M84*BaseDeDatos!$N84 -> 3683.68
B85: 83 | C85: 43952 | D85: 6770397729 | E85: Empresa G | F85: Guaranda | G85: Guaranda | H85: Nancy Gil de la Peña | K85: Café | L85: Bebidas | M85: 644 | N85: 59 | O85: =BaseDeDatos!$M85*BaseDeDatos!$N85 -> 37996
B86: 84 | C86: 44099 | D86: 6622149015 | E86: Empresa J | F86: Esmeraldas | G86: Esmeraldas | H86: Laura Gutiérrez Saenz | I86: Empresa de embarque A | K86: Jalea de fresa | L86: Mermeladas y jaleas | M86: 350 | N86: 27 | O86: =BaseDeDatos!$M86*BaseDeDatos!$N86 -> 9450
B87: 85 | C87: 44071 | D87: 8859429908 | E87: Empresa J | F87: Esmeraldas | G87: Esmeraldas | H87: Laura Gutiérrez Saenz | I87: Empresa de embarque A | K87: Condimento cajún | L87: Condimentos | M87: 308 | N87: 37 | O87: =BaseDeDatos!$M87*BaseDeDatos!$N87 -> 11396
B88: 86 | C88: 44104 | D88: 146252536 | E88: Empresa J | F88: Esmeraldas | G88: Esmeraldas | H88: Laura Gutiérrez Saenz | I88: Empresa de embarque A | K88: Galletas de chocolate | L88: Productos horneados | M88: 128.8 | N88: 75 | O88: =BaseDeDatos!$M88*BaseDeDatos!$N88 -> 9660
B89: 87 | C89: 43866 | D89: 9010865731 | E89: Empresa K | F89: Quito | G89: Pichincha | H89: Ana del Valle Hinojosa | I89: Empresa de embarque C | K89: Ciruelas secas | L89: Frutas secas | M89: 49 | N89: 71 | O89: =BaseDeDatos!$M89*BaseDeDatos!$N89 -> 3479
B90: 88 | C90: 44017 | D90: 9076170123 | E90: Empresa K | F90: Quito | G90: Pichincha | H90: Ana del Valle Hinojosa | I90: Empresa de embarque C | K90: Té verde | L90: Bebidas | M90: 41.86 | N90: 88 | O90: =BaseDeDatos!$M90*BaseDeDatos!$N90 -> 3683.68
B91: 89 | C91: 43924 | D91: 4412491838 | E91: Empresa A | F91: Ambato | G91: Tungurahua | H91: Nancy Gil de la Peña | K91: Té chai | L91: Bebidas | M91: 252 | N91: 55 | O91: =BaseDeDatos!$M91*BaseDeDatos!$N91 -> 13860
B92: 90 | C92: 43964 | D92: 7223227521 | E92: Empresa CC | F92: Guayaquil | G92: Guayas | H92: José de Jesús Morales | I92: Empresa de embarque B | J92: Cheque | K92: Chocolate | L92: Dulces | M92: 178.5 | N92: 14 | O92: =BaseDeDatos!$M92*BaseDeDatos!$N92 -> 2499
B93: 91 | C93: 43994 | D93: 9595973394 | E93: Empresa C | F93: Machala | G93: El Oro | H93: Mayra Aguilar Sepúlveda | I93: Empresa de embarque B | J93: Efectivo | K93: Almejas | L93: Sopas | M93: 135.1 | N93: 43 | O93: =BaseDeDatos!$M93*BaseDeDatos!$N93 -> 5809.3
B94: 92 | C94: 43891 | D94: 2755531090 | E94: Empresa F | F94: Ibarra | G94: Imbabura | H94: Luis Miguel Valdés Garza | I94: Empresa de embarque B | J94: Tarjeta de crédito | K94: Salsa curry | L94: Salsas | M94: 560 | N94: 63 | O94: =BaseDeDatos!$M94*BaseDeDatos!$N94 -> 35280
B95: 93 | C95: 44069 | D95: 5306800000 | E95: Empresa BB | F95: Manta | G95: Manabi | H95: Ana del Valle Hinojosa | I95: Empresa de embarque C | J95: Cheque | K95: Café | L95: Bebidas | M95: 644 | N95: 36 | O95: =BaseDeDatos!$M95*BaseDeDatos!$N95 -> 23184
B96: 94 | C96: 44171 | D96: 6768826719 | E96: Empresa H | F96: Riobamba | G96: Chimborazo | H96: Nancy Gil de la Peña | I96: Empresa de embarque C | J96: Cheque | K96: Chocolate | L96: Dulces | M96: 178.5 | N96: 41 | O96: =BaseDeDatos!$M96*BaseDeDatos!$N96 -> 7318.5
B97: 95 | C97: 43923 | D97: 7945500000 | E97: Empresa J | F97: Esmeraldas | G97: Esmeraldas | H97: Laura Gutiérrez Saenz | I97: Empresa de embarque B | J97: Tarjeta de crédito | K97: Té verde | L97: Bebidas | M97: 41.86 | N97: 35 | O97: =BaseDeDatos!$M97*BaseDeDatos!$N97 -> 1465.1
B98: 96 | C98: 43923 | D98: 4671327569 | E98: Empresa G | F98: Guaranda | G98: Guaranda | H98: Nancy Gil de la Peña | K98: Café | L98: Bebidas | M98: 644 | N98: 31 | O98: =BaseDeDatos!$M98*BaseDeDatos!$N98 -> 19964
B99: 97 | C99: 44100 | D99: 5750783013 | E99: Empresa J | F99: Esmeraldas | G99: Esmeraldas | H99: Laura Gutiérrez Saenz | I99: Empresa de embarque A | K99: Jalea de fresa | L99: Mermeladas y jaleas | M99: 350 | N99: 52 | O99: =BaseDeDatos!$M99*BaseDeDatos!$N99 -> 18200
B100: 98 | C100: 44024 | D100: 1216202808 | E100: Empresa J | F100: Esmeraldas | G100: Esmeraldas | H100: Laura Gutiérrez Saenz | I100: Empresa de embarque A | K100: Condimento cajún | L100: Condimentos | M100: 308 | N100: 30 | O100: =BaseDeDatos!$M100*BaseDeDatos!$N100 -> 9240
B101: 99 | C101: 43934 | D101: 7167041532 | E101: Empresa J | F101: Esmeraldas | G101: Esmeraldas | H101: Laura Gutiérrez Saenz | I101: Empresa de embarque A | K101: Galletas de chocolate | L101: Productos horneados | M101: 128.8 | N101: 41 | O101: =BaseDeDatos!$M101*BaseDeDatos!$N101 -> 5280.8
B102: 100 | C102: 44096 | D102: 2241191338 | E102: Empresa K | F102: Quito | G102: Pichincha | H102: Ana del Valle Hinojosa | I102: Empresa de embarque C | K102: Ciruelas secas | L102: Frutas secas | M102: 49 | N102: 44 | O102: =BaseDeDatos!$M102*BaseDeDatos!$N102 -> 2156
B103: 101 | C103: 44106 | D103: 806264266 | E103: Empresa K | F103: Quito | G103: Pichincha | H103: Ana del Valle Hinojosa | I103: Empresa de embarque C | K103: Té verde | L103: Bebidas | M103: 41.86 | N103: 77 | O103: =BaseDeDatos!$M103*BaseDeDatos!$N103 -> 3223.22
B104: 102 | C104: 43902 | D104: 3820174684 | E104: Empresa A | F104: Ambato | G104: Tungurahua | H104: Nancy Gil de la Peña | K104: Té chai | L104: Bebidas | M104: 252 | N104: 29 | O104: =BaseDeDatos!$M104*BaseDeDatos!$N104 -> 7308
B105: 103 | C105: 44074 | D105: 5541796483 | E105: Empresa A | F105: Ambato | G105: Tungurahua | H105: Nancy Gil de la Peña | K105: Café | L105: Bebidas | M105: 644 | N105: 77 | O105: =BaseDeDatos!$M105*BaseDeDatos!$N105 -> 49588
B106: 104 | C106: 44025 | D106: 7096714976 | E106: Empresa A | F106: Ambato | G106: Tungurahua | H106: Nancy Gil de la Peña | K106: Té verde | L106: Bebidas | M106: 41.86 | N106: 73 | O106: =BaseDeDatos!$M106*BaseDeDatos!$N106 -> 3055.78
B107: 105 | C107: 44160 | D107: 2543114862 | E107: Empresa BB | F107: Manta | G107: Manabi | H107: Ana del Valle Hinojosa | I107: Empresa de embarque C | J107: Tarjeta de crédito | K107: Almejas | L107: Sopas | M107: 135.1 | N107: 74 | O107: =BaseDeDatos!$M107*BaseDeDatos!$N107 -> 9997.4
...

Sheet grf
A1: Etiquetas de fila | B1: Suma de Ventas
A2: feb | B2: 65408
A3: Total general | B3: 65408
A16: Etiquetas de fila | B16: Cuenta de Ventas
A17: José de Jesús Morales | B17: 2
A18: Luis Miguel Valdés Garza | B18: 1
A19: Nancy Gil de la Peña | B19: 1
A20: Total general | B20: 4
A27: Etiquetas de fila | B27: Suma de Ventas
A28: Bebidas | B28: 65408
A29: Total general | B29: 65408
A45: Etiquetas de fila | B45: Suma de Ventas
A46: 0-20000 | B46: 25480
A47: 20000-40000 | B47: 39928
A48: Total general | B48: 65408
A59: Etiquetas de fila | B59: Suma de Ventas | D59: provincias | E59: ventas
A60: Guaranda | B60: 39928 | D60: Azuay | E60: =B60 -> 39928
A61: Guayas | B61: 12348 | D61: Canar | E61: =B61 -> 12348
A62: Imbabura | B62: 13132 | D62: Chimborazo | E62: =B62 -> 13132
A63: Total general | B63: 65408 | D63: El Oro | E63: =B63 -> 65408
D64: Esmeraldas | E64: =B64 -> 0
D65: Guaranda | E65: =B65 -> 0
D66: Guayas | E66: =B66 -> 0
D67: Imbabura | E67: =B67 -> 0
D68: Manabi | E68: =B68 -> 0
D69: Pichincha | E69: =B69 -> 0
D70: Tungurahua | E70: =B70 -> 0

Sheet dash
H1: TABLERO DE CONTROL
G2: CONTROL DE VENTAS

Sheet Graficos
A1: Etiquetas de fila | B1: Suma de Ventas
A2: feb | B2: 150262.9
A3: Total general | B3: 150262.9
A16: Etiquetas de fila | B16: Suma de Ventas
A17: José de Jesús Morales | B17: 21685.5
A18: Laura Gutiérrez Saenz | B18: 39894.4
A19: Luis Miguel Valdés Garza | B19: 25004
A20: Nancy Gil de la Peña | B20: 39928
A21: Robert Zárate Carrillo | B21: 23751
A22: Total general | B22: 150262.9
A28: Etiquetas de fila | B28: Suma de Ventas
A29: Bebidas | B29: 65408
A30: Condimentos | B30: 24640
A31: Dulces | B31: 9337.5
A32: Frutas secas | B32: 25452
A33: Pasta | B33: 23751
A34: Productos horneados | B34: 1674.4
A35: Tarifa de envío
A36: Total general | B36: 150262.9
A46: Etiquetas de fila | B46: Suma de Ventas
A47: <0 o (en blanco)
A48: 0-20000 | B48: 61943.9
A49: 20000-40000 | B49: 88319
A50: Total general | B50: 150262.9
A58: Etiquetas de fila | B58: Suma de Ventas | D58: Provincias | E58: Ventas
A59: Esmeraldas | B59: 39894.4 | D59: Azuay | E59: =GETPIVOTDATA("Ventas",$A$58,"Provincia","Azuay") -> #REF!
A60: Guaranda | B60: 39928 | D60: Canar | E60: =GETPIVOTDATA("Ventas",$A$58,"Provincia","Canar") -> #REF!
A61: Guayas | B61: 45436.5 | D61: Chimborazo | E61: =GETPIVOTDATA("Ventas",$A$58,"Provincia","Chimborazo") -> #REF!
A62: Imbabura | B62: 25004 | D62: El Oro | E62: =GETPIVOTDATA("Ventas",$A$58,"Provincia","El Oro") -> #REF!
A63: Total general | B63: 150262.9 | D63: Esmeraldas | E63: =GETPIVOTDATA("Ventas",$A$58,"Provincia","Esmeraldas") -> 39894.4
D64: Guaranda | E64: =GETPIVOTDATA("Ventas",$A$58,"Provincia","Guaranda") -> 39928
D65: Guayas | E65: =GETPIVOTDATA("Ventas",$A$58,"Provincia","Guayas") -> 45436.5
D66: Imbabura | E66: =GETPIVOTDATA("Ventas",$A$58,"Provincia","Imbabura") -> 25004
D67: Manabi | E67: =GETPIVOTDATA("Ventas",$A$58,"Provincia","Manabi") -> #REF!
D68: Pichincha | E68: =GETPIVOTDATA("Ventas",$A$58,"Provincia","Pichincha") -> #REF!
D69: Tungurahua | E69: =GETPIVOTDATA("Ventas",$A$58,"Provincia","Tungurahua") -> #REF!

Sheet DashBoard
H1: TABLERO DE CONTROL
H3: Control de Ventas
